README.md
setup.cfg
setup.py
aa_camera.egg-info/PKG-INFO
aa_camera.egg-info/SOURCES.txt
aa_camera.egg-info/dependency_links.txt
aa_camera.egg-info/entry_points.txt
aa_camera.egg-info/not-zip-safe
aa_camera.egg-info/requires.txt
aa_camera.egg-info/top_level.txt
camera/__init__.py
camera/camera.py
camera/configs.py
camera/publisher.py
camera/subscriber.py
camera/version.py
testcases/__init__.py
testcases/test_configs.py