Metadata-Version: 2.1
Name: aa-camera
Version: 0.1.6
Summary: a publish&subscrib toolkit
Home-page: https://git.d.com/hik-aa-robots/robots-intelligent-systems/pubsub
Author: shuyuanhao
Author-email: shuyuanhao@cetiti.com
License: UNKNOWN
Keywords: camera info publisher&subscriber
Platform: UNKNOWN
Classifier: Development Status :: 3 - Alpha
Classifier: Topic :: Utilities
Classifier: License :: OSI Approved :: GNU General Public License (GPL)
